{
  "display": {
    "icon": {
      "item": "pyramidplunder:urn"
    },
    "title": {
      "translate": "advancements.pyramidplunder.urns.loot_urn.title"
    },
    "description": {
      "translate": "advancements.pyramidplunder.urns.loot_urn.description"
    },
    "background": "minecraft:textures/block/stone.png"
  },
  "criteria": {
    "loot_urn": {
      "trigger": "minecraft:player_generates_container_loot",
      "conditions": {
        "loot_table": "pyramidplunder:urn"
      }
    }
  }
}